{ "number_of_precincts": 60,
"precincts": [
{
"id": 0,
"coord_x": 0,
"coord_y": 0,
"layers": [
	{"ql": 1, "bytes": 356, "psnr": 26.154883},
	{"ql": 2, "bytes": 410, "psnr": 26.168109},
	{"ql": 3, "bytes": 505, "psnr": 26.184602},
	{"ql": 4, "bytes": 659, "psnr": 26.178169},
	{"ql": 5, "bytes": 1167, "psnr": 26.172801},
	{"ql": 6, "bytes": 2618, "psnr": 26.246675},
	{"ql": 7, "bytes": 4980, "psnr": 26.328336},
	{"ql": 8, "bytes": 8812, "psnr": 26.369278}
	]
},
{
"id": 1,
"coord_x": 128,
"coord_y": 0,
"layers": [
	{"ql": 1, "bytes": 247, "psnr": 26.416189},
	{"ql": 2, "bytes": 323, "psnr": 26.422693},
	{"ql": 3, "bytes": 389, "psnr": 26.410914},
	{"ql": 4, "bytes": 518, "psnr": 26.405296},
	{"ql": 5, "bytes": 1199, "psnr": 26.431919},
	{"ql": 6, "bytes": 2789, "psnr": 26.498598},
	{"ql": 7, "bytes": 5308, "psnr": 26.590620},
	{"ql": 8, "bytes": 8993, "psnr": 26.649196}
	]
},
{
"id": 2,
"coord_x": 256,
"coord_y": 0,
"layers": [
	{"ql": 1, "bytes": 273, "psnr": 26.229112},
	{"ql": 2, "bytes": 324, "psnr": 26.231733},
	{"ql": 3, "bytes": 367, "psnr": 26.234734},
	{"ql": 4, "bytes": 503, "psnr": 26.231617},
	{"ql": 5, "bytes": 1183, "psnr": 26.230252},
	{"ql": 6, "bytes": 2783, "psnr": 26.267177},
	{"ql": 7, "bytes": 5321, "psnr": 26.362309},
	{"ql": 8, "bytes": 8984, "psnr": 26.425283}
	]
},
{
"id": 3,
"coord_x": 384,
"coord_y": 0,
"layers": [
	{"ql": 1, "bytes": 262, "psnr": 26.032202},
	{"ql": 2, "bytes": 307, "psnr": 26.038447},
	{"ql": 3, "bytes": 381, "psnr": 26.025885},
	{"ql": 4, "bytes": 534, "psnr": 26.023805},
	{"ql": 5, "bytes": 1220, "psnr": 26.029841},
	{"ql": 6, "bytes": 2887, "psnr": 26.091735},
	{"ql": 7, "bytes": 5299, "psnr": 26.149638},
	{"ql": 8, "bytes": 9045, "psnr": 26.203416}
	]
},
{
"id": 4,
"coord_x": 512,
"coord_y": 0,
"layers": [
	{"ql": 1, "bytes": 309, "psnr": 25.961341},
	{"ql": 2, "bytes": 363, "psnr": 25.900768},
	{"ql": 3, "bytes": 448, "psnr": 25.924637},
	{"ql": 4, "bytes": 597, "psnr": 25.918191},
	{"ql": 5, "bytes": 1264, "psnr": 25.903713},
	{"ql": 6, "bytes": 2956, "psnr": 25.963312},
	{"ql": 7, "bytes": 5486, "psnr": 26.057189},
	{"ql": 8, "bytes": 9118, "psnr": 26.107171}
	]
},
{
"id": 5,
"coord_x": 640,
"coord_y": 0,
"layers": [
	{"ql": 1, "bytes": 289, "psnr": 25.858154},
	{"ql": 2, "bytes": 324, "psnr": 25.862109},
	{"ql": 3, "bytes": 401, "psnr": 25.878901},
	{"ql": 4, "bytes": 546, "psnr": 25.867041},
	{"ql": 5, "bytes": 1089, "psnr": 25.862068},
	{"ql": 6, "bytes": 2838, "psnr": 25.932329},
	{"ql": 7, "bytes": 5259, "psnr": 25.995990},
	{"ql": 8, "bytes": 8969, "psnr": 26.038597}
	]
},
{
"id": 6,
"coord_x": 768,
"coord_y": 0,
"layers": [
	{"ql": 1, "bytes": 269, "psnr": 25.832416},
	{"ql": 2, "bytes": 324, "psnr": 25.814048},
	{"ql": 3, "bytes": 383, "psnr": 25.819324},
	{"ql": 4, "bytes": 500, "psnr": 25.766613},
	{"ql": 5, "bytes": 1133, "psnr": 25.787055},
	{"ql": 6, "bytes": 2687, "psnr": 25.837986},
	{"ql": 7, "bytes": 5201, "psnr": 25.935473},
	{"ql": 8, "bytes": 8954, "psnr": 25.949714}
	]
},
{
"id": 7,
"coord_x": 896,
"coord_y": 0,
"layers": [
	{"ql": 1, "bytes": 378, "psnr": 25.733125},
	{"ql": 2, "bytes": 486, "psnr": 25.790237},
	{"ql": 3, "bytes": 647, "psnr": 25.847969},
	{"ql": 4, "bytes": 790, "psnr": 25.846568},
	{"ql": 5, "bytes": 1489, "psnr": 25.847277},
	{"ql": 6, "bytes": 3088, "psnr": 25.931277},
	{"ql": 7, "bytes": 5451, "psnr": 25.996216},
	{"ql": 8, "bytes": 9215, "psnr": 26.022359}
	]
},
{
"id": 8,
"coord_x": 1024,
"coord_y": 0,
"layers": [
	{"ql": 1, "bytes": 412, "psnr": 26.462429},
	{"ql": 2, "bytes": 532, "psnr": 26.438228},
	{"ql": 3, "bytes": 672, "psnr": 26.502937},
	{"ql": 4, "bytes": 878, "psnr": 26.501479},
	{"ql": 5, "bytes": 1515, "psnr": 26.516326},
	{"ql": 6, "bytes": 3133, "psnr": 26.614682},
	{"ql": 7, "bytes": 5641, "psnr": 26.729306},
	{"ql": 8, "bytes": 9300, "psnr": 26.762887}
	]
},
{
"id": 9,
"coord_x": 1152,
"coord_y": 0,
"layers": [
	{"ql": 1, "bytes": 655, "psnr": 30.575420},
	{"ql": 2, "bytes": 815, "psnr": 30.805802},
	{"ql": 3, "bytes": 1063, "psnr": 31.109371},
	{"ql": 4, "bytes": 1326, "psnr": 31.327178},
	{"ql": 5, "bytes": 2061, "psnr": 31.528799},
	{"ql": 6, "bytes": 3644, "psnr": 31.778761},
	{"ql": 7, "bytes": 5970, "psnr": 32.121706},
	{"ql": 8, "bytes": 9679, "psnr": 32.294750}
	]
},
{
"id": 10,
"coord_x": 0,
"coord_y": 128,
"layers": [
	{"ql": 1, "bytes": 843, "psnr": 24.710679},
	{"ql": 2, "bytes": 1233, "psnr": 24.941203},
	{"ql": 3, "bytes": 1793, "psnr": 25.123398},
	{"ql": 4, "bytes": 2537, "psnr": 25.311010},
	{"ql": 5, "bytes": 3612, "psnr": 25.403158},
	{"ql": 6, "bytes": 5068, "psnr": 25.476426},
	{"ql": 7, "bytes": 7491, "psnr": 25.546127},
	{"ql": 8, "bytes": 11724, "psnr": 25.593125}
	]
},
{
"id": 11,
"coord_x": 128,
"coord_y": 128,
"layers": [
	{"ql": 1, "bytes": 1112, "psnr": 24.803854},
	{"ql": 2, "bytes": 1620, "psnr": 25.173376},
	{"ql": 3, "bytes": 2244, "psnr": 25.452742},
	{"ql": 4, "bytes": 3075, "psnr": 25.641688},
	{"ql": 5, "bytes": 4139, "psnr": 25.766618},
	{"ql": 6, "bytes": 5766, "psnr": 25.900378},
	{"ql": 7, "bytes": 8222, "psnr": 25.947474},
	{"ql": 8, "bytes": 12509, "psnr": 26.012586}
	]
},
{
"id": 12,
"coord_x": 256,
"coord_y": 128,
"layers": [
	{"ql": 1, "bytes": 1090, "psnr": 25.221544},
	{"ql": 2, "bytes": 1612, "psnr": 25.583652},
	{"ql": 3, "bytes": 2238, "psnr": 25.845552},
	{"ql": 4, "bytes": 2975, "psnr": 26.014748},
	{"ql": 5, "bytes": 4171, "psnr": 26.126849},
	{"ql": 6, "bytes": 5709, "psnr": 26.256150},
	{"ql": 7, "bytes": 8121, "psnr": 26.314658},
	{"ql": 8, "bytes": 12434, "psnr": 26.379405}
	]
},
{
"id": 13,
"coord_x": 384,
"coord_y": 128,
"layers": [
	{"ql": 1, "bytes": 1293, "psnr": 25.691155},
	{"ql": 2, "bytes": 1750, "psnr": 26.049922},
	{"ql": 3, "bytes": 2361, "psnr": 26.346285},
	{"ql": 4, "bytes": 3137, "psnr": 26.575077},
	{"ql": 5, "bytes": 4348, "psnr": 26.731094},
	{"ql": 6, "bytes": 5987, "psnr": 26.851936},
	{"ql": 7, "bytes": 8402, "psnr": 26.920017},
	{"ql": 8, "bytes": 12625, "psnr": 26.986583}
	]
},
{
"id": 14,
"coord_x": 512,
"coord_y": 128,
"layers": [
	{"ql": 1, "bytes": 1495, "psnr": 25.561888},
	{"ql": 2, "bytes": 2072, "psnr": 25.980563},
	{"ql": 3, "bytes": 2894, "psnr": 26.384832},
	{"ql": 4, "bytes": 3723, "psnr": 26.605211},
	{"ql": 5, "bytes": 5058, "psnr": 26.787817},
	{"ql": 6, "bytes": 6508, "psnr": 26.922511},
	{"ql": 7, "bytes": 8769, "psnr": 26.991352},
	{"ql": 8, "bytes": 13044, "psnr": 27.047119}
	]
},
{
"id": 15,
"coord_x": 640,
"coord_y": 128,
"layers": [
	{"ql": 1, "bytes": 1450, "psnr": 24.294891},
	{"ql": 2, "bytes": 1929, "psnr": 24.564195},
	{"ql": 3, "bytes": 2599, "psnr": 24.799563},
	{"ql": 4, "bytes": 3465, "psnr": 24.979712},
	{"ql": 5, "bytes": 4684, "psnr": 25.093213},
	{"ql": 6, "bytes": 6285, "psnr": 25.205712},
	{"ql": 7, "bytes": 8597, "psnr": 25.260924},
	{"ql": 8, "bytes": 12911, "psnr": 25.290910}
	]
},
{
"id": 16,
"coord_x": 768,
"coord_y": 128,
"layers": [
	{"ql": 1, "bytes": 1464, "psnr": 24.815198},
	{"ql": 2, "bytes": 1968, "psnr": 25.199492},
	{"ql": 3, "bytes": 2709, "psnr": 25.428163},
	{"ql": 4, "bytes": 3425, "psnr": 25.630529},
	{"ql": 5, "bytes": 4703, "psnr": 25.752832},
	{"ql": 6, "bytes": 6215, "psnr": 25.863950},
	{"ql": 7, "bytes": 8646, "psnr": 25.954343},
	{"ql": 8, "bytes": 12854, "psnr": 25.995539}
	]
},
{
"id": 17,
"coord_x": 896,
"coord_y": 128,
"layers": [
	{"ql": 1, "bytes": 1387, "psnr": 25.643166},
	{"ql": 2, "bytes": 1934, "psnr": 26.057912},
	{"ql": 3, "bytes": 2741, "psnr": 26.467315},
	{"ql": 4, "bytes": 3671, "psnr": 26.766587},
	{"ql": 5, "bytes": 4958, "psnr": 26.926276},
	{"ql": 6, "bytes": 6524, "psnr": 27.074324},
	{"ql": 7, "bytes": 8662, "psnr": 27.142382},
	{"ql": 8, "bytes": 13021, "psnr": 27.231128}
	]
},
{
"id": 18,
"coord_x": 1024,
"coord_y": 128,
"layers": [
	{"ql": 1, "bytes": 1271, "psnr": 26.186434},
	{"ql": 2, "bytes": 1846, "psnr": 26.753841},
	{"ql": 3, "bytes": 2529, "psnr": 27.112919},
	{"ql": 4, "bytes": 3427, "psnr": 27.367103},
	{"ql": 5, "bytes": 4566, "psnr": 27.571630},
	{"ql": 6, "bytes": 6157, "psnr": 27.735544},
	{"ql": 7, "bytes": 8401, "psnr": 27.865592},
	{"ql": 8, "bytes": 12778, "psnr": 27.931892}
	]
},
{
"id": 19,
"coord_x": 1152,
"coord_y": 128,
"layers": [
	{"ql": 1, "bytes": 1308, "psnr": 27.590365},
	{"ql": 2, "bytes": 1858, "psnr": 28.333964},
	{"ql": 3, "bytes": 2568, "psnr": 28.887119},
	{"ql": 4, "bytes": 3262, "psnr": 29.238414},
	{"ql": 5, "bytes": 4433, "psnr": 29.583699},
	{"ql": 6, "bytes": 6101, "psnr": 29.931803},
	{"ql": 7, "bytes": 8400, "psnr": 30.138487},
	{"ql": 8, "bytes": 12750, "psnr": 30.254409}
	]
},
{
"id": 20,
"coord_x": 0,
"coord_y": 256,
"layers": [
	{"ql": 1, "bytes": 1039, "psnr": 23.261881},
	{"ql": 2, "bytes": 1551, "psnr": 23.475494},
	{"ql": 3, "bytes": 2126, "psnr": 23.607017},
	{"ql": 4, "bytes": 3112, "psnr": 23.786860},
	{"ql": 5, "bytes": 4466, "psnr": 23.877518},
	{"ql": 6, "bytes": 5936, "psnr": 23.926671},
	{"ql": 7, "bytes": 8029, "psnr": 23.960639},
	{"ql": 8, "bytes": 12277, "psnr": 23.984316}
	]
},
{
"id": 21,
"coord_x": 128,
"coord_y": 256,
"layers": [
	{"ql": 1, "bytes": 969, "psnr": 23.326725},
	{"ql": 2, "bytes": 1510, "psnr": 23.601556},
	{"ql": 3, "bytes": 2192, "psnr": 23.793825},
	{"ql": 4, "bytes": 3315, "psnr": 23.984703},
	{"ql": 5, "bytes": 4569, "psnr": 24.042932},
	{"ql": 6, "bytes": 6192, "psnr": 24.155395},
	{"ql": 7, "bytes": 8451, "psnr": 24.204935},
	{"ql": 8, "bytes": 12676, "psnr": 24.231614}
	]
},
{
"id": 22,
"coord_x": 256,
"coord_y": 256,
"layers": [
	{"ql": 1, "bytes": 1846, "psnr": 25.671993},
	{"ql": 2, "bytes": 2513, "psnr": 26.204263},
	{"ql": 3, "bytes": 3433, "psnr": 26.633162},
	{"ql": 4, "bytes": 4456, "psnr": 26.943638},
	{"ql": 5, "bytes": 5707, "psnr": 27.126873},
	{"ql": 6, "bytes": 7263, "psnr": 27.271532},
	{"ql": 7, "bytes": 9361, "psnr": 27.374435},
	{"ql": 8, "bytes": 13651, "psnr": 27.426303}
	]
},
{
"id": 23,
"coord_x": 384,
"coord_y": 256,
"layers": [
	{"ql": 1, "bytes": 1598, "psnr": 25.475873},
	{"ql": 2, "bytes": 2259, "psnr": 25.994249},
	{"ql": 3, "bytes": 3095, "psnr": 26.413847},
	{"ql": 4, "bytes": 4129, "psnr": 26.713044},
	{"ql": 5, "bytes": 5234, "psnr": 26.886218},
	{"ql": 6, "bytes": 6828, "psnr": 27.035700},
	{"ql": 7, "bytes": 8971, "psnr": 27.147756},
	{"ql": 8, "bytes": 13342, "psnr": 27.188660}
	]
},
{
"id": 24,
"coord_x": 512,
"coord_y": 256,
"layers": [
	{"ql": 1, "bytes": 1583, "psnr": 24.168428},
	{"ql": 2, "bytes": 2319, "psnr": 24.633323},
	{"ql": 3, "bytes": 3180, "psnr": 24.903539},
	{"ql": 4, "bytes": 4108, "psnr": 25.081729},
	{"ql": 5, "bytes": 5441, "psnr": 25.247602},
	{"ql": 6, "bytes": 6991, "psnr": 25.335201},
	{"ql": 7, "bytes": 9126, "psnr": 25.396954},
	{"ql": 8, "bytes": 13385, "psnr": 25.435817}
	]
},
{
"id": 25,
"coord_x": 640,
"coord_y": 256,
"layers": [
	{"ql": 1, "bytes": 1559, "psnr": 25.680868},
	{"ql": 2, "bytes": 2263, "psnr": 26.258731},
	{"ql": 3, "bytes": 3012, "psnr": 26.652144},
	{"ql": 4, "bytes": 3975, "psnr": 26.917203},
	{"ql": 5, "bytes": 5266, "psnr": 27.071721},
	{"ql": 6, "bytes": 6703, "psnr": 27.260225},
	{"ql": 7, "bytes": 8892, "psnr": 27.363810},
	{"ql": 8, "bytes": 13252, "psnr": 27.432996}
	]
},
{
"id": 26,
"coord_x": 768,
"coord_y": 256,
"layers": [
	{"ql": 1, "bytes": 1475, "psnr": 24.748219},
	{"ql": 2, "bytes": 2167, "psnr": 25.189790},
	{"ql": 3, "bytes": 3040, "psnr": 25.521722},
	{"ql": 4, "bytes": 4065, "psnr": 25.743569},
	{"ql": 5, "bytes": 5383, "psnr": 25.931419},
	{"ql": 6, "bytes": 7008, "psnr": 26.079022},
	{"ql": 7, "bytes": 8954, "psnr": 26.109048},
	{"ql": 8, "bytes": 13266, "psnr": 26.180805}
	]
},
{
"id": 27,
"coord_x": 896,
"coord_y": 256,
"layers": [
	{"ql": 1, "bytes": 1555, "psnr": 25.369825},
	{"ql": 2, "bytes": 2268, "psnr": 25.965159},
	{"ql": 3, "bytes": 3080, "psnr": 26.433361},
	{"ql": 4, "bytes": 4139, "psnr": 26.749307},
	{"ql": 5, "bytes": 5400, "psnr": 26.904536},
	{"ql": 6, "bytes": 6956, "psnr": 27.062825},
	{"ql": 7, "bytes": 9069, "psnr": 27.156575},
	{"ql": 8, "bytes": 13373, "psnr": 27.205973}
	]
},
{
"id": 28,
"coord_x": 1024,
"coord_y": 256,
"layers": [
	{"ql": 1, "bytes": 1164, "psnr": 24.995981},
	{"ql": 2, "bytes": 1706, "psnr": 25.324033},
	{"ql": 3, "bytes": 2596, "psnr": 25.721499},
	{"ql": 4, "bytes": 3612, "psnr": 25.983093},
	{"ql": 5, "bytes": 5017, "psnr": 26.164769},
	{"ql": 6, "bytes": 6663, "psnr": 26.312066},
	{"ql": 7, "bytes": 8735, "psnr": 26.380044},
	{"ql": 8, "bytes": 13011, "psnr": 26.418513}
	]
},
{
"id": 29,
"coord_x": 1152,
"coord_y": 256,
"layers": [
	{"ql": 1, "bytes": 1262, "psnr": 28.403043},
	{"ql": 2, "bytes": 1937, "psnr": 29.614328},
	{"ql": 3, "bytes": 2669, "psnr": 30.354078},
	{"ql": 4, "bytes": 3631, "psnr": 30.985003},
	{"ql": 5, "bytes": 5002, "psnr": 31.569878},
	{"ql": 6, "bytes": 6531, "psnr": 31.973379},
	{"ql": 7, "bytes": 8676, "psnr": 32.287647},
	{"ql": 8, "bytes": 13030, "psnr": 32.531035}
	]
},
{
"id": 30,
"coord_x": 0,
"coord_y": 384,
"layers": [
	{"ql": 1, "bytes": 766, "psnr": 23.378734},
	{"ql": 2, "bytes": 1194, "psnr": 23.558845},
	{"ql": 3, "bytes": 1735, "psnr": 23.718413},
	{"ql": 4, "bytes": 2969, "psnr": 23.944319},
	{"ql": 5, "bytes": 4233, "psnr": 24.025938},
	{"ql": 6, "bytes": 5737, "psnr": 24.115227},
	{"ql": 7, "bytes": 7843, "psnr": 24.136465},
	{"ql": 8, "bytes": 12091, "psnr": 24.166344}
	]
},
{
"id": 31,
"coord_x": 128,
"coord_y": 384,
"layers": [
	{"ql": 1, "bytes": 704, "psnr": 24.913132},
	{"ql": 2, "bytes": 1142, "psnr": 25.192282},
	{"ql": 3, "bytes": 1698, "psnr": 25.383480},
	{"ql": 4, "bytes": 3041, "psnr": 25.800537},
	{"ql": 5, "bytes": 4211, "psnr": 25.926645},
	{"ql": 6, "bytes": 5887, "psnr": 26.059934},
	{"ql": 7, "bytes": 8079, "psnr": 26.104574},
	{"ql": 8, "bytes": 12363, "psnr": 26.164031}
	]
},
{
"id": 32,
"coord_x": 256,
"coord_y": 384,
"layers": [
	{"ql": 1, "bytes": 1237, "psnr": 26.075480},
	{"ql": 2, "bytes": 1699, "psnr": 26.435875},
	{"ql": 3, "bytes": 2441, "psnr": 26.769587},
	{"ql": 4, "bytes": 3304, "psnr": 27.067684},
	{"ql": 5, "bytes": 4642, "psnr": 27.196723},
	{"ql": 6, "bytes": 6270, "psnr": 27.376594},
	{"ql": 7, "bytes": 8442, "psnr": 27.469903},
	{"ql": 8, "bytes": 12792, "psnr": 27.553715}
	]
},
{
"id": 33,
"coord_x": 384,
"coord_y": 384,
"layers": [
	{"ql": 1, "bytes": 1048, "psnr": 25.023007},
	{"ql": 2, "bytes": 1490, "psnr": 25.332023},
	{"ql": 3, "bytes": 2058, "psnr": 25.543097},
	{"ql": 4, "bytes": 3027, "psnr": 25.759516},
	{"ql": 5, "bytes": 4215, "psnr": 25.898553},
	{"ql": 6, "bytes": 5978, "psnr": 26.057243},
	{"ql": 7, "bytes": 8159, "psnr": 26.114052},
	{"ql": 8, "bytes": 12472, "psnr": 26.184460}
	]
},
{
"id": 34,
"coord_x": 512,
"coord_y": 384,
"layers": [
	{"ql": 1, "bytes": 827, "psnr": 24.793295},
	{"ql": 2, "bytes": 1238, "psnr": 25.054638},
	{"ql": 3, "bytes": 1852, "psnr": 25.321639},
	{"ql": 4, "bytes": 2886, "psnr": 25.564312},
	{"ql": 5, "bytes": 4195, "psnr": 25.734926},
	{"ql": 6, "bytes": 5788, "psnr": 25.865915},
	{"ql": 7, "bytes": 7977, "psnr": 25.930996},
	{"ql": 8, "bytes": 12322, "psnr": 25.958247}
	]
},
{
"id": 35,
"coord_x": 640,
"coord_y": 384,
"layers": [
	{"ql": 1, "bytes": 1219, "psnr": 25.152073},
	{"ql": 2, "bytes": 1693, "psnr": 25.494239},
	{"ql": 3, "bytes": 2476, "psnr": 25.812372},
	{"ql": 4, "bytes": 3419, "psnr": 26.063160},
	{"ql": 5, "bytes": 4767, "psnr": 26.159827},
	{"ql": 6, "bytes": 6338, "psnr": 26.304350},
	{"ql": 7, "bytes": 8544, "psnr": 26.348999},
	{"ql": 8, "bytes": 12862, "psnr": 26.432820}
	]
},
{
"id": 36,
"coord_x": 768,
"coord_y": 384,
"layers": [
	{"ql": 1, "bytes": 1322, "psnr": 24.570922},
	{"ql": 2, "bytes": 1952, "psnr": 24.944863},
	{"ql": 3, "bytes": 2733, "psnr": 25.155888},
	{"ql": 4, "bytes": 3765, "psnr": 25.372354},
	{"ql": 5, "bytes": 5070, "psnr": 25.520781},
	{"ql": 6, "bytes": 6772, "psnr": 25.625591},
	{"ql": 7, "bytes": 8928, "psnr": 25.687650},
	{"ql": 8, "bytes": 13154, "psnr": 25.751558}
	]
},
{
"id": 37,
"coord_x": 896,
"coord_y": 384,
"layers": [
	{"ql": 1, "bytes": 1522, "psnr": 24.814345},
	{"ql": 2, "bytes": 2138, "psnr": 25.256396},
	{"ql": 3, "bytes": 2947, "psnr": 25.575925},
	{"ql": 4, "bytes": 3998, "psnr": 25.799632},
	{"ql": 5, "bytes": 5368, "psnr": 25.969091},
	{"ql": 6, "bytes": 6984, "psnr": 26.084393},
	{"ql": 7, "bytes": 9030, "psnr": 26.199213},
	{"ql": 8, "bytes": 13323, "psnr": 26.245702}
	]
},
{
"id": 38,
"coord_x": 1024,
"coord_y": 384,
"layers": [
	{"ql": 1, "bytes": 1711, "psnr": 25.880526},
	{"ql": 2, "bytes": 2388, "psnr": 26.472967},
	{"ql": 3, "bytes": 3429, "psnr": 27.041648},
	{"ql": 4, "bytes": 4345, "psnr": 27.325431},
	{"ql": 5, "bytes": 5703, "psnr": 27.569109},
	{"ql": 6, "bytes": 7171, "psnr": 27.719458},
	{"ql": 7, "bytes": 9272, "psnr": 27.871938},
	{"ql": 8, "bytes": 13629, "psnr": 27.936589}
	]
},
{
"id": 39,
"coord_x": 1152,
"coord_y": 384,
"layers": [
	{"ql": 1, "bytes": 1794, "psnr": 26.017467},
	{"ql": 2, "bytes": 2529, "psnr": 26.622580},
	{"ql": 3, "bytes": 3478, "psnr": 27.147631},
	{"ql": 4, "bytes": 4396, "psnr": 27.458712},
	{"ql": 5, "bytes": 5797, "psnr": 27.703946},
	{"ql": 6, "bytes": 7163, "psnr": 27.876708},
	{"ql": 7, "bytes": 9266, "psnr": 27.978685},
	{"ql": 8, "bytes": 13640, "psnr": 28.059059}
	]
},
{
"id": 40,
"coord_x": 0,
"coord_y": 512,
"layers": [
	{"ql": 1, "bytes": 877, "psnr": 22.743130},
	{"ql": 2, "bytes": 1387, "psnr": 22.919578},
	{"ql": 3, "bytes": 2110, "psnr": 23.073102},
	{"ql": 4, "bytes": 3235, "psnr": 23.252584},
	{"ql": 5, "bytes": 4615, "psnr": 23.337587},
	{"ql": 6, "bytes": 5914, "psnr": 23.368464},
	{"ql": 7, "bytes": 7918, "psnr": 23.399726},
	{"ql": 8, "bytes": 12232, "psnr": 23.419602}
	]
},
{
"id": 41,
"coord_x": 128,
"coord_y": 512,
"layers": [
	{"ql": 1, "bytes": 839, "psnr": 24.650114},
	{"ql": 2, "bytes": 1385, "psnr": 24.989205},
	{"ql": 3, "bytes": 2085, "psnr": 25.211253},
	{"ql": 4, "bytes": 3259, "psnr": 25.464607},
	{"ql": 5, "bytes": 4533, "psnr": 25.570126},
	{"ql": 6, "bytes": 6153, "psnr": 25.684782},
	{"ql": 7, "bytes": 8418, "psnr": 25.754469},
	{"ql": 8, "bytes": 12585, "psnr": 25.811473}
	]
},
{
"id": 42,
"coord_x": 256,
"coord_y": 512,
"layers": [
	{"ql": 1, "bytes": 609, "psnr": 25.278588},
	{"ql": 2, "bytes": 1076, "psnr": 25.609333},
	{"ql": 3, "bytes": 1818, "psnr": 25.870379},
	{"ql": 4, "bytes": 2714, "psnr": 26.113243},
	{"ql": 5, "bytes": 4046, "psnr": 26.282115},
	{"ql": 6, "bytes": 5644, "psnr": 26.448882},
	{"ql": 7, "bytes": 7904, "psnr": 26.520677},
	{"ql": 8, "bytes": 12229, "psnr": 26.585013}
	]
},
{
"id": 43,
"coord_x": 384,
"coord_y": 512,
"layers": [
	{"ql": 1, "bytes": 474, "psnr": 25.758687},
	{"ql": 2, "bytes": 752, "psnr": 26.021803},
	{"ql": 3, "bytes": 1222, "psnr": 26.209066},
	{"ql": 4, "bytes": 2119, "psnr": 26.422981},
	{"ql": 5, "bytes": 3229, "psnr": 26.539568},
	{"ql": 6, "bytes": 5127, "psnr": 26.716276},
	{"ql": 7, "bytes": 7486, "psnr": 26.821454},
	{"ql": 8, "bytes": 11722, "psnr": 26.881987}
	]
},
{
"id": 44,
"coord_x": 512,
"coord_y": 512,
"layers": [
	{"ql": 1, "bytes": 629, "psnr": 25.236747},
	{"ql": 2, "bytes": 982, "psnr": 25.459297},
	{"ql": 3, "bytes": 1662, "psnr": 25.750979},
	{"ql": 4, "bytes": 2713, "psnr": 25.997702},
	{"ql": 5, "bytes": 3932, "psnr": 26.141233},
	{"ql": 6, "bytes": 5564, "psnr": 26.321352},
	{"ql": 7, "bytes": 7799, "psnr": 26.375788},
	{"ql": 8, "bytes": 12165, "psnr": 26.440755}
	]
},
{
"id": 45,
"coord_x": 640,
"coord_y": 512,
"layers": [
	{"ql": 1, "bytes": 796, "psnr": 25.019165},
	{"ql": 2, "bytes": 1148, "psnr": 25.227948},
	{"ql": 3, "bytes": 1745, "psnr": 25.423790},
	{"ql": 4, "bytes": 2809, "psnr": 25.635875},
	{"ql": 5, "bytes": 4020, "psnr": 25.759525},
	{"ql": 6, "bytes": 5662, "psnr": 25.879265},
	{"ql": 7, "bytes": 8006, "psnr": 25.930094},
	{"ql": 8, "bytes": 12312, "psnr": 25.956682}
	]
},
{
"id": 46,
"coord_x": 768,
"coord_y": 512,
"layers": [
	{"ql": 1, "bytes": 1047, "psnr": 24.578400},
	{"ql": 2, "bytes": 1447, "psnr": 24.832634},
	{"ql": 3, "bytes": 2071, "psnr": 25.052434},
	{"ql": 4, "bytes": 3052, "psnr": 25.268445},
	{"ql": 5, "bytes": 4225, "psnr": 25.368850},
	{"ql": 6, "bytes": 5942, "psnr": 25.494957},
	{"ql": 7, "bytes": 8184, "psnr": 25.548003},
	{"ql": 8, "bytes": 12483, "psnr": 25.592286}
	]
},
{
"id": 47,
"coord_x": 896,
"coord_y": 512,
"layers": [
	{"ql": 1, "bytes": 1054, "psnr": 24.863936},
	{"ql": 2, "bytes": 1430, "psnr": 25.140352},
	{"ql": 3, "bytes": 2102, "psnr": 25.349919},
	{"ql": 4, "bytes": 2935, "psnr": 25.546407},
	{"ql": 5, "bytes": 4178, "psnr": 25.679297},
	{"ql": 6, "bytes": 5847, "psnr": 25.805457},
	{"ql": 7, "bytes": 8174, "psnr": 25.895689},
	{"ql": 8, "bytes": 12443, "psnr": 25.930444}
	]
},
{
"id": 48,
"coord_x": 1024,
"coord_y": 512,
"layers": [
	{"ql": 1, "bytes": 1193, "psnr": 25.054278},
	{"ql": 2, "bytes": 1666, "psnr": 25.377355},
	{"ql": 3, "bytes": 2324, "psnr": 25.603507},
	{"ql": 4, "bytes": 3231, "psnr": 25.837862},
	{"ql": 5, "bytes": 4740, "psnr": 26.015573},
	{"ql": 6, "bytes": 6316, "psnr": 26.130696},
	{"ql": 7, "bytes": 8417, "psnr": 26.198431},
	{"ql": 8, "bytes": 12762, "psnr": 26.246226}
	]
},
{
"id": 49,
"coord_x": 1152,
"coord_y": 512,
"layers": [
	{"ql": 1, "bytes": 1035, "psnr": 25.934631},
	{"ql": 2, "bytes": 1544, "psnr": 26.331567},
	{"ql": 3, "bytes": 2277, "psnr": 26.631215},
	{"ql": 4, "bytes": 3218, "psnr": 26.841578},
	{"ql": 5, "bytes": 4474, "psnr": 27.071026},
	{"ql": 6, "bytes": 6191, "psnr": 27.262055},
	{"ql": 7, "bytes": 8484, "psnr": 27.346707},
	{"ql": 8, "bytes": 12675, "psnr": 27.389176}
	]
},
{
"id": 50,
"coord_x": 0,
"coord_y": 640,
"layers": [
	{"ql": 1, "bytes": 524, "psnr": 24.728743},
	{"ql": 2, "bytes": 755, "psnr": 24.871828},
	{"ql": 3, "bytes": 1074, "psnr": 24.939302},
	{"ql": 4, "bytes": 1828, "psnr": 25.061939},
	{"ql": 5, "bytes": 2626, "psnr": 25.148779},
	{"ql": 6, "bytes": 3881, "psnr": 25.218384},
	{"ql": 7, "bytes": 5645, "psnr": 25.252203},
	{"ql": 8, "bytes": 9494, "psnr": 25.300657}
	]
},
{
"id": 51,
"coord_x": 128,
"coord_y": 640,
"layers": [
	{"ql": 1, "bytes": 786, "psnr": 25.427437},
	{"ql": 2, "bytes": 1128, "psnr": 25.611480},
	{"ql": 3, "bytes": 1624, "psnr": 25.770161},
	{"ql": 4, "bytes": 2416, "psnr": 25.957859},
	{"ql": 5, "bytes": 3422, "psnr": 26.043121},
	{"ql": 6, "bytes": 4797, "psnr": 26.183852},
	{"ql": 7, "bytes": 6677, "psnr": 26.231049},
	{"ql": 8, "bytes": 10434, "psnr": 26.291035}
	]
},
{
"id": 52,
"coord_x": 256,
"coord_y": 640,
"layers": [
	{"ql": 1, "bytes": 695, "psnr": 25.674218},
	{"ql": 2, "bytes": 1002, "psnr": 25.887979},
	{"ql": 3, "bytes": 1470, "psnr": 26.043203},
	{"ql": 4, "bytes": 2366, "psnr": 26.250526},
	{"ql": 5, "bytes": 3524, "psnr": 26.341485},
	{"ql": 6, "bytes": 4980, "psnr": 26.480726},
	{"ql": 7, "bytes": 6831, "psnr": 26.557171},
	{"ql": 8, "bytes": 10468, "psnr": 26.615267}
	]
},
{
"id": 53,
"coord_x": 384,
"coord_y": 640,
"layers": [
	{"ql": 1, "bytes": 533, "psnr": 25.593944},
	{"ql": 2, "bytes": 801, "psnr": 25.801603},
	{"ql": 3, "bytes": 1236, "psnr": 26.025050},
	{"ql": 4, "bytes": 2076, "psnr": 26.162127},
	{"ql": 5, "bytes": 3080, "psnr": 26.296391},
	{"ql": 6, "bytes": 4643, "psnr": 26.407796},
	{"ql": 7, "bytes": 6564, "psnr": 26.496230},
	{"ql": 8, "bytes": 10250, "psnr": 26.549053}
	]
},
{
"id": 54,
"coord_x": 512,
"coord_y": 640,
"layers": [
	{"ql": 1, "bytes": 817, "psnr": 26.420601},
	{"ql": 2, "bytes": 1083, "psnr": 26.568554},
	{"ql": 3, "bytes": 1509, "psnr": 26.724502},
	{"ql": 4, "bytes": 2345, "psnr": 26.940210},
	{"ql": 5, "bytes": 3346, "psnr": 27.052313},
	{"ql": 6, "bytes": 4834, "psnr": 27.182797},
	{"ql": 7, "bytes": 6742, "psnr": 27.254153},
	{"ql": 8, "bytes": 10416, "psnr": 27.304771}
	]
},
{
"id": 55,
"coord_x": 640,
"coord_y": 640,
"layers": [
	{"ql": 1, "bytes": 510, "psnr": 26.570818},
	{"ql": 2, "bytes": 676, "psnr": 26.686012},
	{"ql": 3, "bytes": 1032, "psnr": 26.836586},
	{"ql": 4, "bytes": 1723, "psnr": 27.040251},
	{"ql": 5, "bytes": 2660, "psnr": 27.132909},
	{"ql": 6, "bytes": 4132, "psnr": 27.281480},
	{"ql": 7, "bytes": 6230, "psnr": 27.392146},
	{"ql": 8, "bytes": 9862, "psnr": 27.464550}
	]
},
{
"id": 56,
"coord_x": 768,
"coord_y": 640,
"layers": [
	{"ql": 1, "bytes": 710, "psnr": 25.652358},
	{"ql": 2, "bytes": 1058, "psnr": 25.926734},
	{"ql": 3, "bytes": 1610, "psnr": 26.196369},
	{"ql": 4, "bytes": 2310, "psnr": 26.386827},
	{"ql": 5, "bytes": 3336, "psnr": 26.444001},
	{"ql": 6, "bytes": 4779, "psnr": 26.584622},
	{"ql": 7, "bytes": 6821, "psnr": 26.644059},
	{"ql": 8, "bytes": 10398, "psnr": 26.698159}
	]
},
{
"id": 57,
"coord_x": 896,
"coord_y": 640,
"layers": [
	{"ql": 1, "bytes": 603, "psnr": 25.777343},
	{"ql": 2, "bytes": 957, "psnr": 25.967357},
	{"ql": 3, "bytes": 1443, "psnr": 26.163364},
	{"ql": 4, "bytes": 2375, "psnr": 26.367415},
	{"ql": 5, "bytes": 3446, "psnr": 26.533470},
	{"ql": 6, "bytes": 4927, "psnr": 26.667651},
	{"ql": 7, "bytes": 6721, "psnr": 26.719597},
	{"ql": 8, "bytes": 10412, "psnr": 26.783962}
	]
},
{
"id": 58,
"coord_x": 1024,
"coord_y": 640,
"layers": [
	{"ql": 1, "bytes": 664, "psnr": 26.177061},
	{"ql": 2, "bytes": 966, "psnr": 26.467770},
	{"ql": 3, "bytes": 1397, "psnr": 26.635145},
	{"ql": 4, "bytes": 2185, "psnr": 26.791323},
	{"ql": 5, "bytes": 3232, "psnr": 26.948969},
	{"ql": 6, "bytes": 4740, "psnr": 27.086386},
	{"ql": 7, "bytes": 6740, "psnr": 27.166532},
	{"ql": 8, "bytes": 10334, "psnr": 27.252404}
	]
},
{
"id": 59,
"coord_x": 1152,
"coord_y": 640,
"layers": [
	{"ql": 1, "bytes": 642, "psnr": 33.035391},
	{"ql": 2, "bytes": 929, "psnr": 34.187474},
	{"ql": 3, "bytes": 1369, "psnr": 35.318015},
	{"ql": 4, "bytes": 2032, "psnr": 36.437308},
	{"ql": 5, "bytes": 2944, "psnr": 37.904646},
	{"ql": 6, "bytes": 4363, "psnr": 39.861854},
	{"ql": 7, "bytes": 6376, "psnr": 42.064432},
	{"ql": 8, "bytes": 10059, "psnr": 44.393011}
	]
}
]}
